{
  "ReRoutes": [
    {
      "DownstreamPathTemplate": "/Media/exercise/{tutorialId}",
      "DownstreamScheme": "http",
      "DownstreamHostAndPorts": [
        {
          "Host": "host.docker.internal",
          "Port": 5005
        }
      ],
      "UpstreamPathTemplate": "/exercise-tutorial/{tutorialId}",
      "UpstreamHttpMethod": [ "GET" ],
      "AuthenticationOptions": {
        "AuthenticationProviderKey": "ESport",
        "AllowedScopes": []
      },
      "RouteClaimsRequirement": {
        "Role": "Pupil,LocalAdmin,OrgAdmin"
      },
      "AddHeadersToRequest": {
        "Role": "Claims[Role] > value > |",
        "Id": "Claims[Id] > value > |",
        "Name": "Claims[Name] > value > |",
        "Email": "Claims[Email] > value > |"
      }
    }
  ]
}
